setup.py
ensime_launcher/__init__.py
ensime_launcher.egg-info/PKG-INFO
ensime_launcher.egg-info/SOURCES.txt
ensime_launcher.egg-info/dependency_links.txt
ensime_launcher.egg-info/not-zip-safe
ensime_launcher.egg-info/top_level.txt