Metadata-Version: 1.0
Name: ensime-launcher
Version: 0.1
Summary: Tools for launching ensime from the CLI
Home-page: http://github.com/ensime/ensime-vim
Author: Olivier 'yazgoo' Abdesselam
Author-email: yazgoo@github.com
License: MIT
Platform: UNKNOWN
